Metadata-Version: 1.0
Name: krlvsk-distributions-21c
Version: 1.1
Summary: Gaussian and Binomial distributions
Home-page: UNKNOWN
Author: krlvsk
Author-email: UNKNOWN
License: UNKNOWN
Platform: UNKNOWN
